README.rst
setup.py
mkcss/__init__.py
mkcss.egg-info/PKG-INFO
mkcss.egg-info/SOURCES.txt
mkcss.egg-info/dependency_links.txt
mkcss.egg-info/top_level.txt