Metadata-Version: 1.1
Name: mkcss
Version: 0.1.0
Summary: A CSS generation thing.
Home-page: http://github.com/JuhaniImberg/mkcss/
Author: Juhani Imberg
Author-email: juhani@imberg.com
License: MIT
Platform: UNKNOWN
Classifier: Development Status :: 3 - Alpha
Classifier: Environment :: Console
Classifier: Intended Audience :: Developers
Classifier: License :: OSI Approved :: MIT License
Classifier: Programming Language :: Python :: 2.6
Classifier: Programming Language :: Python :: 2.7
Classifier: Programming Language :: Python :: 3.2
Classifier: Programming Language :: Python :: 3.3
